hypigu/__init__.py
hypigu/braid.py
hypigu/constructors.py
hypigu/gen_functions.py
hypigu/globals.py
hypigu/graded_poset.py
tests/__init__.py
tests/test_braid.py
tests/test_constructors.py
hypigu-2.0.0.dist-info/LICENSE
hypigu-2.0.0.dist-info/METADATA
hypigu-2.0.0.dist-info/WHEEL
hypigu-2.0.0.dist-info/top_level.txt
hypigu-2.0.0.dist-info/RECORD
