Metadata-Version: 2.1
Name: hypigu
Version: 2.0.0
Summary: A SageMath package that provides functions to compute the Igusa local zeta function associated with hyperplane arrangements.
Home-page: https://joshmaglione.github.io/hypigu/
Author: Joshua Maglione
Author-email: joshmaglione@gmail.com
Project-URL: Bug Tracker, https://github.com/joshmaglione/hypigu/issues
Keywords: SageMath,hyperplane arrangements,Igusa zeta functions,topological zeta functions,Flag Hilbert--Poincare series
Classifier: Programming Language :: Python :: 3
Classifier: License :: OSI Approved :: MIT License
Classifier: Operating System :: OS Independent
License-File: LICENSE
